st_card_component_0/__init__.py
st_card_component_0/frontend/build/asset-manifest.json
st_card_component_0/frontend/build/bootstrap.min.css
st_card_component_0/frontend/build/index.html
st_card_component_0/frontend/build/precache-manifest.f19dfee9a6f4eeae2336c9b1b0c09b5b.js
st_card_component_0/frontend/build/service-worker.js
st_card_component_0/frontend/build/static/css/2.b2d9eb83.chunk.css
st_card_component_0/frontend/build/static/css/2.b2d9eb83.chunk.css.map
st_card_component_0/frontend/build/static/js/2.16ca7662.chunk.js
st_card_component_0/frontend/build/static/js/2.16ca7662.chunk.js.LICENSE.txt
st_card_component_0/frontend/build/static/js/2.16ca7662.chunk.js.map
st_card_component_0/frontend/build/static/js/main.394c92f7.chunk.js
st_card_component_0/frontend/build/static/js/main.394c92f7.chunk.js.map
st_card_component_0/frontend/build/static/js/runtime-main.44d30fc2.js
st_card_component_0/frontend/build/static/js/runtime-main.44d30fc2.js.map
st_card_component_0/frontend/build/static/media/roboto-all-400-normal.62b936e1.woff
st_card_component_0/frontend/build/static/media/roboto-cyrillic-400-normal.d9ac47c7.woff2
st_card_component_0/frontend/build/static/media/roboto-cyrillic-ext-400-normal.c00467dc.woff2
st_card_component_0/frontend/build/static/media/roboto-greek-400-normal.28668857.woff2
st_card_component_0/frontend/build/static/media/roboto-greek-ext-400-normal.35de3738.woff2
st_card_component_0/frontend/build/static/media/roboto-latin-400-normal.15d9f621.woff2
st_card_component_0/frontend/build/static/media/roboto-latin-ext-400-normal.87ace200.woff2
st_card_component_0/frontend/build/static/media/roboto-vietnamese-400-normal.ca3b09b6.woff2
st_card_component_0-0.0.2.dist-info/LICENSE
st_card_component_0-0.0.2.dist-info/METADATA
st_card_component_0-0.0.2.dist-info/WHEEL
st_card_component_0-0.0.2.dist-info/top_level.txt
st_card_component_0-0.0.2.dist-info/RECORD
