Metadata-Version: 2.1
Name: st-card-component-0
Version: 0.0.2
Home-page: 
Author: 
Author-email: 
Requires-Python: >=3.6
License-File: LICENSE
Requires-Dist: streamlit (>=0.63)
